README.txt
setup.py
txu1/__init__.py
txu1/api_v1.py
txu1/cli_tool.py
txu1.egg-info/PKG-INFO
txu1.egg-info/SOURCES.txt
txu1.egg-info/dependency_links.txt
txu1.egg-info/entry_points.txt
txu1.egg-info/requires.txt
txu1.egg-info/top_level.txt