Metadata-Version: 1.1
Name: txu1
Version: 13.06.0
Summary: Twisted-based async interface for Ubuntu One Files Cloud REST API v1
Home-page: https://github.com/mk-fg/txu1
Author: Mike Kazantsev
Author-email: mk.fraggod@gmail.com
License: WTFPL
Keywords: ubuntu one,u1,ubuntu,one,twisted,sso,async,api,rest,json,storage,storage provider,file hosting
Platform: UNKNOWN
Classifier: Development Status :: 4 - Beta
Classifier: Environment :: Plugins
Classifier: Framework :: Twisted
Classifier: Intended Audience :: Developers
Classifier: Intended Audience :: Information Technology
Classifier: License :: OSI Approved
Classifier: Operating System :: OS Independent
Classifier: Programming Language :: Python
Classifier: Programming Language :: Python :: 2.7
Classifier: Programming Language :: Python :: 2 :: Only
Classifier: Topic :: Internet
Classifier: Topic :: System :: Archiving
Classifier: Topic :: System :: Filesystems
